{
    "+Add Nickname": "+Add Nickname",
    "$40 need to paid while exchanging for a new physical card": "$40 need to paid while exchanging for a new physical card",
    "Access Location": "Access Location",
    "Account": "Account",
    "Activities": "Activities",
    "Activity": "Activity",
    "Add coupons and save more": "Add coupons and save more",
    "Add New Card": "Add New Card",
    "Add your card and manage your recharges, activities, gameplays and more with smartfun": "Add your card and manage your recharges, activities, gameplays and more with smartfun",
    "All": "All",
    "Apply Coupon": "Apply Coupon",
    "APPLY FILTER": "APPLY FILTER",
    "Are you sure you want to remove the card?": "Are you sure you want to remove the card?",
    "At least 12 - 15 characters long, and can contain letters, numbers and symbols": "At least 12 - 15 characters long, and can contain letters, numbers and symbols",
    "BACK TO HOME": "BACK TO HOME",
    "BACK TO LOGIN": "BACK TO LOGIN",
    "Balance": "Balance",
    "Balance consumed during gameplay": "Balance consumed during gameplay",
    "Became Member": "Became Member",
    "Below Games are excluded": "Below Games are excluded",
    "Below Pagkages are excluded": "Below Pagkages are excluded",
    "Bill Details": "Bill Details",
    "BLOCK & ISSUE REPLACEMENT": "BLOCK & ISSUE REPLACEMENT",
    "Blocked": "Blocked",
    "Bonus": "Bonus",
    "Bonus Balance Details": "Bonus Balance Details",
    "Booked By": "Booked By",
    "Booking ID": "Booking ID",
    "Bookings": "Bookings",
    "Build Version": "Build Version",
    "Buy a Card": "Buy a Card",
    "BUY NEW CARD": "BUY NEW CARD",
    "BUY NOW": "BUY NOW",
    "By Loggin in you agree yo our Termns of Service and Privacy Policy": "By Loggin in you agree yo our Termns of Service and Privacy Policy",
    "Can be used to play below games": "Can be used to play below games",
    "Can be used to purhcase below packages": "Can be used to purhcase below packages",
    "CANCEL": "CANCEL",
    "Card Activities": "Card Activities",
    "Card Added Successfully": "Card Added Successfully",
    "CARD DETAILS": "CARD DETAILS",
    "Card Game": "Card Game",
    "Card Nickname (for easy identification)": "Card Nickname (for easy identification)",
    "Card Number": "Card Number",
    "Card Successfully Blocked": "Card Successfully Blocked",
    "Cardgames": "Cardgames",
    "Cart": "Cart",
    "Category": "Category",
    "CCV": "CCV",
    "CHANGE PASSWORD": "CHANGE PASSWORD",
    "Clear All": "Clear All",
    "Close": "Close",
    "Completed": "Completed",
    "CONFIRM LOCATION": "CONFIRM LOCATION",
    "Confirm Password": "Confirm Password",
    "Coupons": "Coupons",
    "Courtesy": "Courtesy",
    "CREDITS": "CREDITS",
    "CUSTOMER INFORMATION": "CUSTOMER INFORMATION",
    "Date of Birth": "Date of Birth",
    "Didnt receive the OTP?": "Didnt receive the OTP?",
    "Didn't Receive?": "Didn't Receive?",
    "Discount": "Discount",
    "Discount (Coupon)": "Discount (Coupon)",
    "Discount (Offer)": "Discount (Offer)",
    "DONE": "DONE",
    "Don't worry about password": "Don't worry about password",
    "DOWNLOAD": "DOWNLOAD",
    "Earn another LP": "Earn another LP",
    "Edit Photo": "Edit Photo",
    "Email Address": "Email Address",
    "Email Notifications": "Email Notifications",
    "ENABLE LOCATION SERVICES": "ENABLE LOCATION SERVICES",
    "Enter": "Enter",
    "Enter Card Number": "Enter Card Number",
    "Enter here": "Enter here",
    "Enter registered phone number or email": "Enter registered phone number or email",
    "Enter the credits you want to transfer": "Enter the credits you want to transfer",
    "Enter the OTP to verify": "Enter the OTP to verify",
    "Enter the OTP to verify your mail ID": "Enter the OTP to verify your mail ID",
    "Enter the OTP yo verify your mobile number": "Enter the OTP yo verify your mobile number",
    "Enter your registered email or mobile below to receive password reset instructions": "Enter your registered email or mobile below to receive password reset instructions",
    "Entered value is more than available 200 credits": "Entered value is more than available 200 credits",
    "Events": "Events",
    "Exclusive Offers on Cards": "Exclusive Offers on Cards",
    "Expired": "Expired",
    "Expiring by": "Expiring by",
    "Features $ Terms": "Features $ Terms",
    "Filter": "Filter",
    "First Name": "First Name",
    "For you": "For you",
    "Forgot Password?": "Forgot Password?",
    "From": "From",
    "Game Plays": "Game Plays",
    "Get Balance": "Get Balance",
    "Gold": "Gold",
    "Gold Member": "Gold Member",
    "Grab these deals ASAP": "Grab these deals ASAP",
    "Guests": "Guests",
    "Have a Coupon code?": "Have a Coupon code?",
    "Have an Account": "Have an Account",
    "Help": "Help",
    "Here is your virtual card": "Here is your virtual card",
    "Hi There, Complete the following details to setup your account and continue using Smartfun App.": "Hi There, Complete the following details to setup your account and continue using Smartfun App.",
    "Home": "Home",
    "If you enable location services wqe can show you the nearest Store and Store specific offers, deals and prices for you": "If you enable location services wqe can show you the nearest Store and Store specific offers, deals and prices for you",
    "I'll Locate the Store Manually": "I'll Locate the Store Manually",
    "Invalid Entry": "Invalid Entry",
    "Last Name": "Last Name",
    "Legal": "Legal",
    "Like the App?": "Like the App?",
    "LINK A CARD": "LINK A CARD",
    "LOGIN": "LOGIN",
    "LOGIN WITH OTP": "LOGIN WITH OTP",
    "LOGIN WITH PASSWORD": "LOGIN WITH PASSWORD",
    "Logout": "Logout",
    "Lost Card": "Lost Card",
    "Lost Card Terms": "Lost Card Terms",
    "Loyalty": "Loyalty",
    "LOYALTY POINTS DETAILS": "LOYALTY POINTS DETAILS",
    "Loyalty Points Earned": "Loyalty Points Earned",
    "Loyalty Points Earning Details": "Loyalty Points Earning Details",
    "Manage your notifications settings": "Manage your notifications settings",
    "Membership": "Membership",
    "MEMBERSHIP F&Q": "MEMBERSHIP F&Q",
    "MEMBERSHIP REWARDS": "MEMBERSHIP REWARDS",
    "Membership rewards are loaded on to your primary card": "Membership rewards are loaded on to your primary card",
    "Mobile Number": "Mobile Number",
    "More": "More",
    "More Actions": "More Actions",
    "My Bookings": "My Bookings",
    "My Cards": "My Cards",
    "Name on Card": "Name on Card",
    "New Password": "New Password",
    "New to smartfun?": "New to smartfun?",
    "Notification Preferences": "Notification Preferences",
    "Notifications": "Notifications",
    "OKAY !": "OKAY !",
    "OKAY, GOT IT": "OKAY, GOT IT",
    "Oops! We were unable to process your payment at the moment. Any money deducted from your account will be reverted back to the source of payment in 2-5 working days.": "Oops! We were unable to process your payment at the moment. Any money deducted from your account will be reverted back to the source of payment in 2-5 working days.",
    "Or Continue with social Logins": "Or Continue with social Logins",
    "Other's Card": "Other's Card",
    "OTP Verification": "OTP Verification",
    "Package": "Package",
    "Password": "Password",
    "Password changed Succesfully": "Password changed Succesfully",
    "Password Login": "Password Login",
    "Payable Amount": "Payable Amount",
    "Payment Failed": "Payment Failed",
    "Payment Options": "Payment Options",
    "Phone": "Phone",
    "Platinum": "Platinum",
    "Play": "Play",
    "Price Range": "Price Range",
    "PROCEED TO PAY": "PROCEED TO PAY",
    "Promotional Notifications": "Promotional Notifications",
    "Qty": "Qty",
    "QUICK CARD RECHARGES": "QUICK CARD RECHARGES",
    "Quick Links": "Quick Links",
    "Rate us in the App Store": "Rate us in the App Store",
    "Read FAQs or Get in touch": "Read FAQs or Get in touch",
    "Receive emails about new offers and deals": "Receive emails about new offers and deals",
    "Receive push notifications about new offers and deals on your mobile phone": "Receive push notifications about new offers and deals on your mobile phone",
    "Receive push notifications about new transactions made.": "Receive push notifications about new transactions made.",
    "Recent Searches": "Recent Searches",
    "Recent Transfers": "Recent Transfers",
    "Recharge": "Recharge",
    "Recharge Amount": "Recharge Amount",
    "RECHARGE NOW": "RECHARGE NOW",
    "Recharge now for extend the card's validity or move your credits to a new card to save it from expiration": "Recharge now for extend the card's validity or move your credits to a new card to save it from expiration",
    "Recharge Successful": "Recharge Successful",
    "Recharge Value": "Recharge Value",
    "Recommended For You": "Recommended For You",
    "Reference Id": "Reference Id",
    "REMOVE": "REMOVE",
    "Remove Saved Card": "Remove Saved Card",
    "Replacement of": "Replacement of",
    "Report your lost card and get replacement": "Report your lost card and get replacement",
    "RESEND in 30 secs": "RESEND in 30 secs",
    "Resent OTP in 30 Seconds": "Resent OTP in 30 Seconds",
    "RESET NOW": "RESET NOW",
    "Reset Password": "Reset Password",
    "Reset Password link is sent your registered mobile number": "Reset Password link is sent your registered mobile number",
    "RETRY PAYMENT": "RETRY PAYMENT",
    "Rewards": "Rewards",
    "Rs": "Rs",
    "SAVE": "SAVE",
    "SAVE CARD": "SAVE CARD",
    "SAVED ON THE BILL WITH THE COUPON": "SAVED ON THE BILL WITH THE COUPON",
    "Search": "Search",
    "Select Entitlement": "Select Entitlement",
    "Select Location": "Select Location",
    "SEND": "SEND",
    "SEND OTP": "SEND OTP",
    "Setup your account": "Setup your account",
    "Show this bar code on site to get a new physical card. A Payment of $40 will be charged for the replacement on site.": "Show this bar code on site to get a new physical card. A Payment of $40 will be charged for the replacement on site.",
    "SIGN UP": "SIGN UP",
    "Silver": "Silver",
    "Since": "Since",
    "SmartFun / My Bookings": "SmartFun / My Bookings",
    "Tap on the QR Code to use it for scanning at Game Plays": "Tap on the QR Code to use it for scanning at Game Plays",
    "Tax": "Tax",
    "Term of use and Privacy policy": "Term of use and Privacy policy",
    "This Card cannot be used for any further transactions. A temporary card will be issued, exchange the temporary card for a new physical card at site": "This Card cannot be used for any further transactions. A temporary card will be issued, exchange the temporary card for a new physical card at site",
    "This card has expired on 01 Jan 2023": "This card has expired on 01 Jan 2023",
    "Tickets": "Tickets",
    "Time": "Time",
    "To": "To",
    "Today": "Today",
    "Today's Offers": "Today's Offers",
    "Total Bonus Balance": "Total Bonus Balance",
    "Transaction Details": "Transaction Details",
    "Transactional Notifications": "Transactional Notifications",
    "Transfer Bonus": "Transfer Bonus",
    "Transfer Credit": "Transfer Credit",
    "Transfer credits from one card to another": "Transfer credits from one card to another",
    "Transfer From": "Transfer From",
    "Transfer Successful": "Transfer Successful",
    "Transfer To": "Transfer To",
    "Transfer to Card": "Transfer to Card",
    "TrxId": "TrxId",
    "TRY WITH ANOTHER PAYMENT OPTION": "TRY WITH ANOTHER PAYMENT OPTION",
    "UNAVAILABLE NOW": "UNAVAILABLE NOW",
    "Unread": "Unread",
    "Upcoming": "Upcoming",
    "Username": "Username",
    "Valid for 11 months from the date of purchase": "Valid for 11 months from the date of purchase",
    "Valid From": "Valid From",
    "Valid Thru": "Valid Thru",
    "Valid To": "Valid To",
    "Value Loaded": "Value Loaded",
    "Verified": "Verified",
    "Verify": "Verify",
    "VERIFY & PROCEED": "VERIFY & PROCEED",
    "Verify Email": "Verify Email",
    "Verify Mobile Number": "Verify Mobile Number",
    "View all your gameplay records": "View all your gameplay records",
    "View Details": "View Details",
    "VIEW RECEIPT": "VIEW RECEIPT",
    "View the rewards you have earned": "View the rewards you have earned",
    "View Transactions, Recharges and more": "View Transactions, Recharges and more",
    "VIEW VIRTUAL CARD": "VIEW VIRTUAL CARD",
    "Virtual Card": "Virtual Card",
    "WAIVERS": "WAIVERS",
    "We have mailed you an OTP": "We have mailed you an OTP",
    "We have sent an OTP to your mobile number": "We have sent an OTP to your mobile number",
    "We have transferred all your credits and other points to a new virtual card": "We have transferred all your credits and other points to a new virtual card",
    "Yesterday": "Yesterday",
    "You can now use this card as a virtual card to carry out the card functionalities": "You can now use this card as a virtual card to carry out the card functionalities",
    "You have successfully recharged credits on to your": "You have successfully recharged credits on to your",
    "You have successfully transfered credits to card number": "You have successfully transfered credits to card number",
    "You will no longer be able to use this card. But you can still view the Gameplay history and Activity details": "You will no longer be able to use this card. But you can still view the Gameplay history and Activity details",
    "Your card has been blocked, and you no longer will be able to use it": "Your card has been blocked, and you no longer will be able to use it",
    "Your card has been blocked, based on your request. You no longer will be able to use it. This card will be removed from smartfun once you get the new physical card": "Your card has been blocked, based on your request. You no longer will be able to use it. This card will be removed from smartfun once you get the new physical card",
    "Your card will expire in 2 days": "Your card will expire in 2 days",
    "Your cards will be saved securey saved for faster payments. CVV numbers not be saved": "Your cards will be saved securey saved for faster payments. CVV numbers not be saved",
    "Your new card has been added to your account": "Your new card has been added to your account",
    "Your new password must be different from previously used passwords.": "Your new password must be different from previously used passwords."
}